odoo/addons/ssi_stock_promotion_operation/README.rst
odoo/addons/ssi_stock_promotion_operation/__init__.py
odoo/addons/ssi_stock_promotion_operation/__manifest__.py
odoo/addons/ssi_stock_promotion_operation/data/stock_picking_type_category_data.xml
odoo/addons/ssi_stock_promotion_operation/security/ir_module_category_data.xml
odoo/addons/ssi_stock_promotion_operation/security/res_group_data.xml
odoo/addons/ssi_stock_promotion_operation/static/description/icon.png
odoo/addons/ssi_stock_promotion_operation/views/customer_promotion_views.xml
odoo/addons/ssi_stock_promotion_operation/views/supplier_promotion_views.xml
odoo14_addon_ssi_stock_promotion_operation-14.0.1.1.0.dist-info/METADATA
odoo14_addon_ssi_stock_promotion_operation-14.0.1.1.0.dist-info/WHEEL
odoo14_addon_ssi_stock_promotion_operation-14.0.1.1.0.dist-info/top_level.txt
odoo14_addon_ssi_stock_promotion_operation-14.0.1.1.0.dist-info/RECORD
